mvcrender-0.0.8.dist-info/METADATA
mvcrender-0.0.8.dist-info/WHEEL
mvcrender-0.0.8.dist-info/top_level.txt
mvcrender-0.0.8.dist-info/RECORD
mvcrender-0.0.8.dist-info/licenses/LICENSE
mvcrender/__init__.py
mvcrender/blend/_native.c
mvcrender/blend/_native.cpython-313-x86_64-linux-musl.so
mvcrender/blend/_native.pyi
mvcrender/blend/__init__.py
mvcrender/autocrop/_native.c
mvcrender/autocrop/_native.cpython-313-x86_64-linux-musl.so
mvcrender/autocrop/_native.pyi
mvcrender/autocrop/__init__.py
mvcrender/draw/_native.c
mvcrender/draw/_native.cpython-313-x86_64-linux-musl.so
mvcrender/draw/_native.pyi
mvcrender/draw/__init__.py
mvcrender/material/_native.c
mvcrender/material/_native.cpython-313-x86_64-linux-musl.so
mvcrender/material/_native.pyi
mvcrender/material/__init__.py
mvcrender/material/material.py
mvcrender/rooms/_native.c
mvcrender/rooms/_native.cpython-313-x86_64-linux-musl.so
mvcrender/rooms/_native.pyi
mvcrender/rooms/__init__.py
