Metadata-Version: 2.4
Name: mvcrender
Version: 0.0.8
Summary: High-performance C extensions for image processing in Home Assistant - AutoCrop, Blend, Draw, and Rooms processing for Valetudo Map Parser
Author-email: Sandro Cantarella <gsca075@gmail.com>
License-Expression: Apache-2.0
Project-URL: Homepage, https://github.com/sca075/mvcrender
Project-URL: Repository, https://github.com/sca075/mvcrender
Project-URL: Issues, https://github.com/sca075/mvcrender/issues
Project-URL: Changelog, https://github.com/sca075/mvcrender/releases
Keywords: image-processing,home-assistant,valetudo,map-parser,numpy,c-extension,autocrop,blend,draw,rooms,vacuum-map
Classifier: Development Status :: 4 - Beta
Classifier: Intended Audience :: Developers
Classifier: Operating System :: OS Independent
Classifier: Programming Language :: Python :: 3
Classifier: Programming Language :: Python :: 3.13
Classifier: Programming Language :: C
Classifier: Topic :: Software Development :: Libraries :: Python Modules
Classifier: Topic :: Scientific/Engineering :: Image Processing
Classifier: Topic :: Home Automation
Requires-Python: >=3.13
License-File: LICENSE
Requires-Dist: numpy>=2.1
Dynamic: license-file
